scholar/__init__.py
scholar/__main__.py
scholar/article.py
scholar/constants.py
scholar/main.py
scholar/scholar.py
scholar-1.0.6.dist-info/DESCRIPTION.rst
scholar-1.0.6.dist-info/METADATA
scholar-1.0.6.dist-info/RECORD
scholar-1.0.6.dist-info/WHEEL
scholar-1.0.6.dist-info/entry_points.txt
scholar-1.0.6.dist-info/metadata.json
scholar-1.0.6.dist-info/top_level.txt
