Metadata-Version: 1.1
Name: scholar
Version: 1.0.6
Summary: UNKNOWN
Home-page: https://github.com/AnthonyBloomer/scholar
Author: Anthony Bloomer
Author-email: ant0@protonmail.ch
License: UNKNOWN
Keywords: springer
Platform: UNKNOWN
Classifier: Development Status :: 5 - Production/Stable
Classifier: Environment :: Console
Classifier: Intended Audience :: Developers
Classifier: Intended Audience :: End Users/Desktop
Classifier: Operating System :: OS Independent
Classifier: License :: OSI Approved :: MIT License
Classifier: Programming Language :: Python
Classifier: Programming Language :: Python :: 2.7
Classifier: Programming Language :: Python :: 3
Classifier: Programming Language :: Python :: 3.3
Classifier: Programming Language :: Python :: 3.4
Classifier: Programming Language :: Python :: 3.5
Classifier: Programming Language :: Python :: 3.6
